setup.py
SGA_TEST_1741/__init__.py
SGA_TEST_1741/function.py
SGA_TEST_1741/testing.py
SGA_TEST_1741.egg-info/PKG-INFO
SGA_TEST_1741.egg-info/SOURCES.txt
SGA_TEST_1741.egg-info/dependency_links.txt
SGA_TEST_1741.egg-info/top_level.txt