Metadata-Version: 1.0
Name: SGA-TEST-1741
Version: 0.1.0
Summary: A package to check whether the input number is prime or non prime
Home-page: UNKNOWN
Author: Ishtpreet
Author-email: ishtpreet.singh@sganalytics.com
License: LICENSE.txt
Platform: UNKNOWN
